{
  "version": "0.3.14-fixed",
  "steps": [
    {
      "tag": "UpdateField",
      "model": "User",
      "field": "drinkingLocation",
      "arity": "Optional"
    },
    {
      "tag": "UpdateField",
      "model": "User",
      "field": "profile",
      "arity": "Optional"
    },
    {
      "tag": "UpdateField",
      "model": "Profile",
      "field": "user",
      "arity": "Optional"
    },
    {
      "tag": "UpdateField",
      "model": "Profile",
      "field": "userId",
      "arity": "Optional"
    },
    {
      "tag": "UpdateField",
      "model": "DrinkingLocation",
      "field": "user",
      "arity": "Optional"
    },
    {
      "tag": "UpdateField",
      "model": "DrinkingLocation",
      "field": "userId",
      "arity": "Optional"
    }
  ]
}